metamk/__init__.py
metamk/impl.py
metamk-0.0.4.dist-info/licenses/LICENSE
metamk-0.0.4.dist-info/METADATA
metamk-0.0.4.dist-info/WHEEL
metamk-0.0.4.dist-info/top_level.txt
metamk-0.0.4.dist-info/RECORD
