Metadata-Version: 2.4
Name: metamk
Version: 0.0.4
Summary: A minimal framework for explicit phase structuring around the main action (inspired by AAA pattern and Design by Contract)
Author: minoru_jp
License: MIT License
Project-URL: Homepage, https://github.com/minoru-jp/metamk
Project-URL: Source, https://github.com/minoru-jp/metamk
Project-URL: Issues, https://github.com/minoru-jp/metamk/issues
Keywords: AAA,test,mark,divide,separate,structuring,dbc,contract,async,framework
Classifier: Programming Language :: Python :: 3
Classifier: License :: OSI Approved :: MIT License
Classifier: Development Status :: 3 - Alpha
Classifier: Intended Audience :: Developers
Classifier: Topic :: Software Development :: Libraries :: Python Modules
Requires-Python: >=3.10
License-File: LICENSE
Dynamic: license-file
